lomo_optim/__init__.py
lomo_optim/adalomo.py
lomo_optim/lomo.py
lomo_optim-0.1.1.dist-info/LICENSE
lomo_optim-0.1.1.dist-info/METADATA
lomo_optim-0.1.1.dist-info/WHEEL
lomo_optim-0.1.1.dist-info/top_level.txt
lomo_optim-0.1.1.dist-info/RECORD
