Metadata-Version: 2.1
Name: lomo-optim
Version: 0.1.1
Summary: LOMO: LOw-Memory Optimization
Author-email: Kai Lv <klv21@m.fudan.edu.cn>
License: MIT License
Project-URL: Homepage, https://github.com/OpenLMLab/LOMO
Project-URL: Documentation, https://openlmlab-collie.readthedocs.io/zh-cn/latest/api/generated/collie.optim.Lomo.html
Project-URL: Repository, https://github.com/OpenLMLab/LOMO.git
Classifier: Topic :: Scientific/Engineering :: Artificial Intelligence
Requires-Python: >=3.8
License-File: LICENSE
Requires-Dist: transformers
Requires-Dist: torch
